LICENSE
README.md
pyproject.toml
setup.py
cuml_rfext/RandomForestClassifier.py
cuml_rfext/RandomForestRegressor.py
cuml_rfext/__init__.py
cuml_rfext.egg-info/PKG-INFO
cuml_rfext.egg-info/SOURCES.txt
cuml_rfext.egg-info/dependency_links.txt
cuml_rfext.egg-info/not-zip-safe
cuml_rfext.egg-info/requires.txt
cuml_rfext.egg-info/top_level.txt
src/get_feature_importances.cpp
src/main.cpp